Workbook

Sheet README
A1: COMM5005 T3 2026 - Group G6 - Childtime Australia location study
A2: LGAs: Ku-ring-gai, Bayside, North Sydney (verify boundaries on ABS Census map; 2021 LGA geography)
A3: Yellow cells = inputs to fill from sources (no data has been entered yet). White cells = formulas.
A4: Sheets: Data (inputs + sources) > Indicators (normalised measures) > Costs (staffing/site) > Scoring (weighted) > Summary (report table + charts)
A5: Record source, reference year and access date for every input in the Data sheet.

Sheet Data
A1: Indicator | B1: Unit | C1: Ku-ring-gai | D1: Bayside | E1: North Sydney | F1: Source | G1: Reference year | H1: Date accessed | I1: Notes / proxy
A2: Total population | B2: persons | F2: ABS Census 2021 Community Profile (G01) | G2: 2021
A3: Children aged 0-4 | B3: persons | F3: ABS Census 2021 (G04) | G3: 2021
A4: Children aged 0-4 as share check | B4: persons | F4: (formula in Indicators)
A5: Families with children under 5 / couple families with children | B5: families | F5: ABS Census 2021 (G25/G29) | G5: 2021
A6: Median weekly household income | B6: $/week | F6: ABS Census 2021 (G02) | G6: 2021
A7: Median weekly family income | B7: $/week | F7: ABS Census 2021 (G02) | G7: 2021
A8: Employment rate (labour force employed / aged 15+) | B8: % | F8: ABS Census 2021 (G43) | G8: 2021
A9: Female labour force participation | B9: % | F9: ABS Census 2021 (G43) | G9: 2021
A10: Bachelor degree or above (15+) | B10: % | F10: ABS Census 2021 (G46) | G10: 2021
A11: Approved childcare centres (centre-based day care) in LGA | B11: count | F11: ACECQA National Register / MyChild | G11: 2026
A12: Approved centre-based places (if available) | B12: places | F12: ACECQA / DoE childcare data | G12: 2026
A13: Land/lease price proxy: median rent for commercial/childcare site | B13: $/m2/yr | F13: Realcommercial / CoStar / Valuer-General; document proxy | G13: 2026
A14: Land value proxy ($/m2, ~1,500 m2 site) | B14: $/m2 | F14: NSW Valuer General land values | G14: 2026
A15: Median weekly rent (residential, cost proxy) | B15: $/week | F15: ABS Census 2021 (G02) | G15: 2021
A16: Peak-hour drive time to LGA centre (accessibility) | B16: minutes | F16: Google Maps / TfNSW | G16: 2026
... A19: Wage benchmark adjustment vs base | B19: % | F19: Assumption - justify | G19: 2026
A21: Staffing wage assumptions (annual, $)
A22: Role | B22: Headcount | C22: Annual salary ($) - base | D22: On-cost rate (super/leave etc.)
A23: Director | B23: 1 | D23: 0.15
A24: Child activity coordinator (teacher) | B24: 10 | D24: 0.15
A25: Chef | B25: 1 | D25: 0.15
A26: Cleaner | B26: 1 | D26: 0.15
A27: Facilities maintenance | B27: 1 | D27: 0.15

Sheet Indicators
A1: Normalised indicator | B1: Definition / denominator rationale | C1: Ku-ring-gai | D1: Bayside | E1: North Sydney
A2: Children 0-4 per 100 residents | B2: Age-structure intensity; removes population size effect | C2: =Data!C3/Data!C2*100 | D2: =Data!D3/Data!D2*100 | E2: =Data!E3/Data!E2*100
A3: Children 0-4 per km2 | B3: Catchment density (driving catchment) | C3: =Data!C3/Data!C18 | D3: =Data!D3/Data!D18 | E3: =Data!E3/Data!E18
A4: Centres per 1,000 children 0-4 | B4: Supply proxy (not places/occupancy) - lower = less competition | C4: =Data!C11/Data!C3*1000 | D4: =Data!D11/Data!D3*1000 | E4: =Data!E11/Data!E3*1000
A5: Children 0-4 per centre | B5: Potential demand per competitor | C5: =Data!C3/Data!C11 | D5: =Data!D3/Data!D11 | E5: =Data!E3/Data!E11
A6: Places per child 0-4 | B6: Supply coverage if places data available | C6: =IFERROR(Data!C12/Data!C3,"n/a") | D6: =IFERROR(Data!D12/Data!D3,"n/a") | E6: =IFERROR(Data!E12/Data!E3,"n/a")
A7: Income / affordability index (HH income, Ku-ring-gai=100) | B7: Ability to pay; indicator only, not demand | C7: =Data!C6/Data!$C$6*100 | D7: =Data!D6/Data!$C$6*100 | E7: =Data!E6/Data!$C$6*100
A8: Land value index (Ku-ring-gai=100) | B8: Relative site cost proxy | C8: =IFERROR(Data!C14/Data!$C$14*100,"") | D8: =IFERROR(Data!D14/Data!$C$14*100,"") | E8: =IFERROR(Data!E14/Data!$C$14*100,"")

Sheet Costs
A1: Annual staffing cost | B1: Formula | C1: Ku-ring-gai | D1: Bayside | E1: North Sydney
A2: Base staffing cost ($/yr) | B2: SUMPRODUCT(headcount x salary x (1+on-cost)) | C2: =SUMPRODUCT(Data!$B$23:$B$27,Data!$C$23:$C$27*(1+Data!$D$23:$D$27)) | D2: =SUMPRODUCT(Data!$B$23:$B$27,Data!$C$23:$C$27*(1+Data!$D$23:$D$27)) | E2: =SUMPRODUCT(Data!$B$23:$B$27,Data!$C$23:$C$27*(1+Data!$D$23:$D$27))
A3: Location wage adjustment | B3: from Data row 19 | C3: =Data!C19 | D3: =Data!D19 | E3: =Data!E19
A4: Adjusted staffing cost ($/yr) | B4: base x (1+adj) | C4: =C2*(1+C3) | D4: =D2*(1+D3) | E4: =E2*(1+E3)
A5: Site area required (m2) | B5: Rooms 300+kitchen 50+office 40+storage 30+playgrounds 600+car park 400 = 1,420; min site 1,500 | C5: 1500 | D5: 1500 | E5: 1500
A6: Site cost proxy ($) | B6: land $/m2 x 1,500 | C6: =Data!C14*C5 | D6: =Data!D14*D5 | E6: =Data!E14*E5
A7: Annual cost per child 0-4 in LGA ($) | B7: adjusted staffing / children 0-4 (scale indicator) | C7: =C4/Data!C3 | D7: =D4/Data!D3 | E7: =E4/Data!E3

Sheet Scoring
A1: Criterion | B1: Weight (assumption) | C1: Direction (+1 higher better, -1 lower better) | D1: Ku-ring-gai | E1: Bayside | F1: North Sydney
A2: Children 0-4 per km2 (density) | B2: 0.2 | C2: 1 | D2: =IFERROR(IF($C2=1,(Indicators!C3-MIN(Indicators!C3:E3))/(MAX(Indicators!C3:E3)-MIN(Indicators!C3:E3)),(MAX(Indicators!C3:E3)-Indicators!C3)/(MAX(Indicators!C3:E3)-MIN(Indicators!C3:E3))),"") | E2: =IFERROR(IF($C2=1,(Indicators!D3-MIN(Indicators!C3:E3))/(MAX(Indicators!C3:E3)-MIN(Indicators!C3:E3)),(MAX(Indicators!C3:E3)-Indicators!D3)/(MAX(Indicators!C3:E3)-MIN(Indicators!C3:E3))),"") | F2: =IFERROR(IF($C2=1,(Indicators!E3-MIN(Indicators!C3:E3))/(MAX(Indicators!C3:E3)-MIN(Indicators!C3:E3)),(MAX(Indicators!C3:E3)-Indicators!E3)/(MAX(Indicators!C3:E3)-MIN(Indicators!C3:E3))),"")
A3: Children per centre (low competition) | B3: 0.2 | C3: 1 | D3: =IFERROR(IF($C3=1,(Indicators!C5-MIN(Indicators!C5:E5))/(MAX(Indicators!C5:E5)-MIN(Indicators!C5:E5)),(MAX(Indicators!C5:E5)-Indicators!C5)/(MAX(Indicators!C5:E5)-MIN(Indicators!C5:E5))),"") | E3: =IFERROR(IF($C3=1,(Indicators!D5-MIN(Indicators!C5:E5))/(MAX(Indicators!C5:E5)-MIN(Indicators!C5:E5)),(MAX(Indicators!C5:E5)-Indicators!D5)/(MAX(Indicators!C5:E5)-MIN(Indicators!C5:E5))),"") | F3: =IFERROR(IF($C3=1,(Indicators!E5-MIN(Indicators!C5:E5))/(MAX(Indicators!C5:E5)-MIN(Indicators!C5:E5)),(MAX(Indicators!C5:E5)-Indicators!E5)/(MAX(Indicators!C5:E5)-MIN(Indicators!C5:E5))),"")
A4: Household income | B4: 0.15 | C4: 1 | D4: =IFERROR(IF($C4=1,(Data!C6-MIN(Data!C6:E6))/(MAX(Data!C6:E6)-MIN(Data!C6:E6)),(MAX(Data!C6:E6)-Data!C6)/(MAX(Data!C6:E6)-MIN(Data!C6:E6))),"") | E4: =IFERROR(IF($C4=1,(Data!D6-MIN(Data!C6:E6))/(MAX(Data!C6:E6)-MIN(Data!C6:E6)),(MAX(Data!C6:E6)-Data!D6)/(MAX(Data!C6:E6)-MIN(Data!C6:E6))),"") | F4: =IFERROR(IF($C4=1,(Data!E6-MIN(Data!C6:E6))/(MAX(Data!C6:E6)-MIN(Data!C6:E6)),(MAX(Data!C6:E6)-Data!E6)/(MAX(Data!C6:E6)-MIN(Data!C6:E6))),"")
A5: Land value proxy | B5: 0.2 | C5: -1 | D5: =IFERROR(IF($C5=1,(Data!C14-MIN(Data!C14:E14))/(MAX(Data!C14:E14)-MIN(Data!C14:E14)),(MAX(Data!C14:E14)-Data!C14)/(MAX(Data!C14:E14)-MIN(Data!C14:E14))),"") | E5: =IFERROR(IF($C5=1,(Data!D14-MIN(Data!C14:E14))/(MAX(Data!C14:E14)-MIN(Data!C14:E14)),(MAX(Data!C14:E14)-Data!D14)/(MAX(Data!C14:E14)-MIN(Data!C14:E14))),"") | F5: =IFERROR(IF($C5=1,(Data!E14-MIN(Data!C14:E14))/(MAX(Data!C14:E14)-MIN(Data!C14:E14)),(MAX(Data!C14:E14)-Data!E14)/(MAX(Data!C14:E14)-MIN(Data!C14:E14))),"")
A6: Peak-hour accessibility (minutes) | B6: 0.15 | C6: -1 | D6: =IFERROR(IF($C6=1,(Data!C16-MIN(Data!C16:E16))/(MAX(Data!C16:E16)-MIN(Data!C16:E16)),(MAX(Data!C16:E16)-Data!C16)/(MAX(Data!C16:E16)-MIN(Data!C16:E16))),"") | E6: =IFERROR(IF($C6=1,(Data!D16-MIN(Data!C16:E16))/(MAX(Data!C16:E16)-MIN(Data!C16:E16)),(MAX(Data!C16:E16)-Data!D16)/(MAX(Data!C16:E16)-MIN(Data!C16:E16))),"") | F6: =IFERROR(IF($C6=1,(Data!E16-MIN(Data!C16:E16))/(MAX(Data!C16:E16)-MIN(Data!C16:E16)),(MAX(Data!C16:E16)-Data!E16)/(MAX(Data!C16:E16)-MIN(Data!C16:E16))),"")
A7: Children 0-4 (market size) | B7: 0.1 | C7: 1 | D7: =IFERROR(IF($C7=1,(Data!C3-MIN(Data!C3:E3))/(MAX(Data!C3:E3)-MIN(Data!C3:E3)),(MAX(Data!C3:E3)-Data!C3)/(MAX(Data!C3:E3)-MIN(Data!C3:E3))),"") | E7: =IFERROR(IF($C7=1,(Data!D3-MIN(Data!C3:E3))/(MAX(Data!C3:E3)-MIN(Data!C3:E3)),(MAX(Data!C3:E3)-Data!D3)/(MAX(Data!C3:E3)-MIN(Data!C3:E3))),"") | F7: =IFERROR(IF($C7=1,(Data!E3-MIN(Data!C3:E3))/(MAX(Data!C3:E3)-MIN(Data!C3:E3)),(MAX(Data!C3:E3)-Data!E3)/(MAX(Data!C3:E3)-MIN(Data!C3:E3))),"")
A8: Weighted score (0-1) | B8: =SUM(B2:B7) | D8: =SUMPRODUCT($B$2:$B$7,D2:D7) | E8: =SUMPRODUCT($B$2:$B$7,E2:E7) | F8: =SUMPRODUCT($B$2:$B$7,F2:F7)
A9: Rank | D9: =RANK(D8,$D$8:$F$8) | E9: =RANK(E8,$D$8:$F$8) | F9: =RANK(F8,$D$8:$F$8)

Sheet Summary
A1: Indicator | B1: Unit | C1: Ku-ring-gai | D1: Bayside | E1: North Sydney
A2: Population | B2: persons | C2: =Data!C2 | D2: =Data!D2 | E2: =Data!E2
A3: Children 0-4 | B3: persons | C3: =Data!C3 | D3: =Data!D3 | E3: =Data!E3
A4: Median HH income | B4: $/wk | C4: =Data!C6 | D4: =Data!D6 | E4: =Data!E6
A5: Centres per 1,000 children | B5: ratio | C5: =Indicators!C4 | D5: =Indicators!D4 | E5: =Indicators!E4
A6: Children per km2 | B6: ratio | C6: =Indicators!C3 | D6: =Indicators!D3 | E6: =Indicators!E3
A7: Land value ($/m2) | B7: $/m2 | C7: =Data!C14 | D7: =Data!D14 | E7: =Data!E14
A8: Adj. staffing cost | B8: $/yr | C8: =Costs!C4 | D8: =Costs!D4 | E8: =Costs!E4
A9: Weighted score | B9: 0-1 | C9: =Scoring!D8 | D9: =Scoring!E8 | E9: =Scoring!F8
